cmaths/__init__.py
cmaths/add.py
cmaths-0.1.0.dist-info/METADATA
cmaths-0.1.0.dist-info/WHEEL
cmaths-0.1.0.dist-info/top_level.txt
cmaths-0.1.0.dist-info/RECORD
